MANIFEST.in
README
curlish.py
setup.cfg
setup.py
curlish.egg-info/PKG-INFO
curlish.egg-info/SOURCES.txt
curlish.egg-info/dependency_links.txt
curlish.egg-info/entry_points.txt
curlish.egg-info/not-zip-safe
curlish.egg-info/top_level.txt