Metadata-Version: 1.1
Name: curlish
Version: 1.21
Summary: A wrapper for curl that adds OAuth support
Home-page: http://github.com/fireteam/curlish
Author: Fireteam Ltd.
Author-email: support@fireteam.net
License: UNKNOWN
Platform: UNKNOWN
Classifier: License :: OSI Approved :: BSD License
Classifier: Programming Language :: Python
